setup.cfg
setup.py
judge/__init__.py
judge/decide.py
judge/predicates.py
judge.egg-info/PKG-INFO
judge.egg-info/SOURCES.txt
judge.egg-info/dependency_links.txt
judge.egg-info/top_level.txt